setup.py
vdian/__init__.py
vdian/api.py
vdian.egg-info/PKG-INFO
vdian.egg-info/SOURCES.txt
vdian.egg-info/dependency_links.txt
vdian.egg-info/requires.txt
vdian.egg-info/top_level.txt