Metadata-Version: 1.0
Name: vdian
Version: 0.1
Summary: 微店 python SDK
Home-page: https://coding.net/u/jeff/p/vdian/git
Author: jeff kit
Author-email: bbmyth@gmail.com
License: UNKNOWN
Platform: UNKNOWN
